mcp_server/__init__.py
mcp_server/check_run.py
mcp_server/env_loader.py
mcp_server/server.py
mcp_server/test_server.py
mcp_server/test_tool_discovery.py
mcp_server/test_usage.py
mcp_server/verify_tools.py
mcp_server/base_function/__init__.py
mcp_server/base_function/patent_claim.py
mcp_server/base_function/patent_images.py
mcp_server/base_function/patent_law_status.py
mcp_server/base_function/patent_search.py
mcp_server/base_function/patent_similar.py
mcp_server/base_function/patent_specification.py
mcp_server/config/gunicorn_conf.py
patent_mcp_server_shunjian-0.1.1.dist-info/licenses/LICENSE
patent_mcp_server_shunjian-0.1.1.dist-info/METADATA
patent_mcp_server_shunjian-0.1.1.dist-info/WHEEL
patent_mcp_server_shunjian-0.1.1.dist-info/entry_points.txt
patent_mcp_server_shunjian-0.1.1.dist-info/top_level.txt
patent_mcp_server_shunjian-0.1.1.dist-info/RECORD
