Metadata-Version: 2.4
Name: patent-mcp-server-shunjian
Version: 0.1.1
Summary: MCP Server for Patent Search Functions - integrates with Baiten Patent API
Author-email: lysander-z-f-q <15312371297@example.com>
License: MIT
Project-URL: Homepage, https://github.com/lysander-z-f-q/patent-mcp-server
Project-URL: Repository, https://github.com/lysander-z-f-q/patent-mcp-server
Keywords: mcp,patent,search,baiten,mcp-server
Classifier: Development Status :: 3 - Alpha
Classifier: Intended Audience :: Developers
Classifier: License :: OSI Approved :: MIT License
Classifier: Programming Language :: Python :: 3
Classifier: Programming Language :: Python :: 3.10
Classifier: Programming Language :: Python :: 3.11
Classifier: Programming Language :: Python :: 3.12
Requires-Python: >=3.10
License-File: LICENSE
Requires-Dist: fastmcp>=2.13.0
Requires-Dist: requests>=2.31.0
Requires-Dist: python-dotenv>=1.0.0
Dynamic: license-file
